ecgai_training_data_physionet/__init__.py
ecgai_training_data_physionet/main.py
ecgai_training_data_physionet/models.py
ecgai_training_data_physionet/physionet.py
ecgai_training_data_physionet/ptbxl.py
tests/__init__.py
tests/test_models.py
tests/test_ptbxl.py
ecgai_training_data_physionet-0.0.12.dist-info/LICENSE
ecgai_training_data_physionet-0.0.12.dist-info/METADATA
ecgai_training_data_physionet-0.0.12.dist-info/WHEEL
ecgai_training_data_physionet-0.0.12.dist-info/top_level.txt
ecgai_training_data_physionet-0.0.12.dist-info/RECORD
