Metadata-Version: 2.1
Name: ecgai-training-data-physionet
Version: 0.0.12
Summary: Function to access ECG data from physionet.org
Home-page: https://github.com/Ecg-Ai-com/ecgai-training-data-physionet
Author: Rob Clapham
Author-email: 
License: UNKNOWN
Project-URL: Bug Tracker, https://github.com/Ecg-Ai-com/ecgai-training-data-physionet/issues
Platform: UNKNOWN
Classifier: Programming Language :: Python :: 3
Classifier: Development Status :: 3 - Alpha
Classifier: Intended Audience :: Developers
Classifier: Topic :: Scientific/Engineering :: Medical Science Apps.
Classifier: License :: OSI Approved :: GNU General Public License v3 or later (GPLv3+)
Classifier: Operating System :: OS Independent
Requires-Python: >=3.9
License-File: LICENSE
